nodewui/__init__.py
nodewui/app.py
nodewui/media/index.html
nodewui-0.1.2.dist-info/entry_points.txt
nodewui-0.1.2.dist-info/WHEEL
nodewui-0.1.2.dist-info/METADATA
nodewui-0.1.2.dist-info/RECORD
