Metadata-Version: 2.1
Name: nodewui
Version: 0.1.2
Summary: A simple web interface to get information from Bitcoin Cash node and similar software
Home-page: https://gitlab.com/uak/nodewui/
Keywords: bitcoin
Author: uak
Author-email: 4626956-uak@users.noreply.gitlab.com
Requires-Python: >=3.8,<4.0
Classifier: Programming Language :: Python :: 3
Classifier: Programming Language :: Python :: 3.10
Classifier: Programming Language :: Python :: 3.8
Classifier: Programming Language :: Python :: 3.9
Requires-Dist: CherryPy (>=18.8.0,<19.0.0)
Requires-Dist: requests (>=2.28.1,<3.0.0)
Project-URL: Repository, https://gitlab.com/uak/nodewui/
